get_ua
