Metadata-Version: 2.1
Name: get-ua
Version: 20231212.3
Summary: Simple library for generating random user agents
Home-page: https://github.com/anteverta/get_ua
Author: Dmitriy Kotenko
Author-email: antevertapro@gmail.com
Classifier: Programming Language :: Python :: 3
Classifier: Operating System :: OS Independent
License-File: LICENSE
